pcntoolkit/__init__.py
pcntoolkit/normative.py
pcntoolkit/normative_model.py
pcntoolkit/dataio/__init__.py
pcntoolkit/dataio/data_factory.py
pcntoolkit/dataio/fileio.py
pcntoolkit/dataio/norm_data.py
pcntoolkit/math_functions/__init__.py
pcntoolkit/math_functions/basis_function.py
pcntoolkit/math_functions/factorize.py
pcntoolkit/math_functions/likelihood.py
pcntoolkit/math_functions/prior.py
pcntoolkit/math_functions/scaler.py
pcntoolkit/math_functions/shash.py
pcntoolkit/math_functions/thrive.py
pcntoolkit/math_functions/warp.py
pcntoolkit/regression_model/__init__.py
pcntoolkit/regression_model/blr.py
pcntoolkit/regression_model/factory.py
pcntoolkit/regression_model/hbr.py
pcntoolkit/regression_model/regression_model.py
pcntoolkit/regression_model/test_model.py
pcntoolkit/util/__init__.py
pcntoolkit/util/evaluator.py
pcntoolkit/util/job_observer.py
pcntoolkit/util/model_comparison.py
pcntoolkit/util/output.py
pcntoolkit/util/paths.py
pcntoolkit/util/plotter.py
pcntoolkit/util/runner.py
pcntoolkit-1.1.1.dist-info/licenses/LICENSE
pcntoolkit-1.1.1.dist-info/METADATA
pcntoolkit-1.1.1.dist-info/WHEEL
pcntoolkit-1.1.1.dist-info/entry_points.txt
pcntoolkit-1.1.1.dist-info/top_level.txt
pcntoolkit-1.1.1.dist-info/RECORD
